dynamo_dictionary/__init__.py
dynamo_dictionary-1.0.1.dist-info/LICENSE
dynamo_dictionary-1.0.1.dist-info/METADATA
dynamo_dictionary-1.0.1.dist-info/WHEEL
dynamo_dictionary-1.0.1.dist-info/top_level.txt
dynamo_dictionary-1.0.1.dist-info/RECORD
