Metadata-Version: 2.1
Name: dynamo-dictionary
Version: 1.0.1
Summary: Easily Use DynamoDB as a key-value format.
Home-page: https://github.com/da-huin/dynamo_dictionary
Author: JunYeong Park
Author-email: dahuin000@gmail.com
License: MIT
Download-URL: https://github.com/da-huin/dynamo_dictionary/archive/master.zip
Platform: UNKNOWN
Classifier: Programming Language :: Python :: 3
Requires-Dist: boto3
